[
    {
        "name": "WNJD_203_86"
    },
    {
        "name": "WNJD_203_116"
    },
    {
        "name": "WNJD_203_92"
    },
    {
        "name": "WNJD_203_200"
    },
    {
        "name": "WNJD_203_130"
    },
    {
        "name": "WNJD_203_172"
    },
    {
        "name": "WNJD_203_40"
    },
    {
        "name": "WNJD_203_6"
    },
    {
        "name": "WNJD_203_124"
    },
    {
        "name": "WNJD_203_213"
    },
    {
        "name": "WNJD_203_87"
    },
    {
        "name": "WNJD_203_20"
    },
    {
        "name": "WNJD_203_147"
    },
    {
        "name": "WNJD_203_226"
    },
    {
        "name": "WNJD_203_106"
    },
    {
        "name": "WNJD_203_132"
    },
    {
        "name": "WNJD_203_186"
    },
    {
        "name": "WNJD_203_214"
    },
    {
        "name": "WNJD_203_207"
    },
    {
        "name": "WNJD_203_126"
    },
    {
        "name": "WNJD_203_216"
    },
    {
        "name": "WNJD_203_233"
    },
    {
        "name": "WNJD_203_89"
    },
    {
        "name": "WNJD_203_223"
    },
    {
        "name": "WNJD_203_139"
    },
    {
        "name": "WNJD_203_138"
    },
    {
        "name": "WNJD_203_161"
    },
    {
        "name": "WNJD_203_195"
    },
    {
        "name": "WNJD_203_202"
    },
    {
        "name": "WNJD_203_33"
    },
    {
        "name": "WNJD_203_14"
    },
    {
        "name": "WNJD_203_15"
    },
    {
        "name": "WNJD_203_197"
    },
    {
        "name": "WNJD_203_101"
    },
    {
        "name": "WNJD_203_201"
    },
    {
        "name": "WNJD_203_165"
    },
    {
        "name": "WNJD_203_11"
    },
    {
        "name": "WNJD_203_84"
    },
    {
        "name": "WNJD_203_230"
    },
    {
        "name": "WNJD_203_96"
    },
    {
        "name": "WNJD_203_111"
    },
    {
        "name": "WNJD_203_9"
    },
    {
        "name": "WNJD_203_10"
    },
    {
        "name": "WNJD_203_32"
    },
    {
        "name": "WNJD_203_212"
    },
    {
        "name": "WNJD_203_129"
    },
    {
        "name": "WNJD_203_16"
    },
    {
        "name": "WNJD_203_219"
    },
    {
        "name": "WNJD_203_83"
    },
    {
        "name": "WNJD_203_210"
    },
    {
        "name": "WNJD_203_30"
    },
    {
        "name": "WNJD_203_155"
    },
    {
        "name": "WNJD_203_225"
    },
    {
        "name": "WNJD_203_2"
    },
    {
        "name": "WNJD_203_176"
    },
    {
        "name": "WNJD_203_39"
    },
    {
        "name": "WNJD_203_93"
    },
    {
        "name": "WNJD_302_2"
    },
    {
        "name": "WNJD_203_134"
    },
    {
        "name": "WNJD_203_199"
    },
    {
        "name": "WNJD_203_82"
    },
    {
        "name": "WNJD_203_1"
    },
    {
        "name": "WNJD_203_229"
    },
    {
        "name": "WNJD_203_27"
    },
    {
        "name": "WNJD_203_182"
    },
    {
        "name": "WNJD_203_38"
    },
    {
        "name": "WNJD_203_18"
    },
    {
        "name": "WNJD_302_42"
    },
    {
        "name": "WNJD_203_90"
    },
    {
        "name": "WNJD_203_218"
    },
    {
        "name": "WNJD_203_184"
    },
    {
        "name": "WNJD_203_208"
    },
    {
        "name": "WNJD_203_100"
    },
    {
        "name": "WNJD_203_145"
    },
    {
        "name": "WNJD_203_215"
    },
    {
        "name": "WNJD_203_183"
    },
    {
        "name": "WNJD_203_104"
    },
    {
        "name": "WNJD_203_98"
    },
    {
        "name": "WNJD_203_188"
    },
    {
        "name": "WNJD_203_193"
    },
    {
        "name": "WNJD_203_5"
    },
    {
        "name": "WNJD_203_112"
    },
    {
        "name": "WNJD_203_97"
    },
    {
        "name": "WNJD_203_168"
    },
    {
        "name": "WNJD_203_163"
    },
    {
        "name": "WNJD_203_236"
    },
    {
        "name": "WNJD_203_107"
    },
    {
        "name": "WNJD_203_221"
    },
    {
        "name": "WNJD_203_137"
    },
    {
        "name": "WNJD_203_171"
    },
    {
        "name": "WNJD_203_13"
    },
    {
        "name": "WNJD_203_180"
    },
    {
        "name": "WNJD_203_120"
    },
    {
        "name": "WNJD_203_181"
    },
    {
        "name": "WNJD_203_3"
    },
    {
        "name": "WNJD_203_118"
    },
    {
        "name": "WNJD_203_228"
    },
    {
        "name": "WNJD_203_150"
    },
    {
        "name": "WNJD_203_157"
    },
    {
        "name": "WNJD_203_127"
    },
    {
        "name": "WNJD_203_102"
    },
    {
        "name": "WNJD_203_117"
    },
    {
        "name": "WNJD_203_31"
    },
    {
        "name": "WNJD_203_131"
    },
    {
        "name": "WNJD_203_108"
    },
    {
        "name": "WNJD_203_35"
    },
    {
        "name": "WNJD_203_190"
    },
    {
        "name": "WNJD_203_177"
    },
    {
        "name": "WNJD_203_156"
    },
    {
        "name": "WNJD_203_113"
    },
    {
        "name": "WNJD_203_128"
    },
    {
        "name": "WNJD_203_123"
    },
    {
        "name": "WNJD_203_94"
    },
    {
        "name": "WNJD_203_235"
    },
    {
        "name": "WNJD_203_22"
    },
    {
        "name": "WNJD_203_121"
    },
    {
        "name": "WNJD_203_179"
    },
    {
        "name": "WNJD_203_23"
    },
    {
        "name": "WNJD_203_67"
    },
    {
        "name": "WNJD_203_69"
    },
    {
        "name": "WNJD_203_222"
    },
    {
        "name": "WNJD_203_135"
    },
    {
        "name": "WNJD_203_175"
    },
    {
        "name": "WNJD_203_68"
    },
    {
        "name": "WNJD_203_4"
    },
    {
        "name": "WNJD_203_170"
    },
    {
        "name": "WNJD_203_91"
    },
    {
        "name": "WNJD_203_174"
    },
    {
        "name": "WNJD_203_105"
    },
    {
        "name": "WNJD_203_143"
    },
    {
        "name": "WNJD_203_109"
    },
    {
        "name": "WNJD_203_205"
    },
    {
        "name": "WNJD_203_26"
    },
    {
        "name": "WNJD_203_142"
    },
    {
        "name": "WNJD_203_17"
    },
    {
        "name": "WNJD_203_133"
    },
    {
        "name": "WNJD_203_99"
    },
    {
        "name": "WNJD_203_34"
    },
    {
        "name": "WNJD_203_37"
    },
    {
        "name": "WNJD_203_144"
    },
    {
        "name": "WNJD_203_19"
    },
    {
        "name": "WNJD_203_209"
    },
    {
        "name": "WNJD_203_224"
    },
    {
        "name": "WNJD_203_72"
    },
    {
        "name": "WNJD_203_211"
    },
    {
        "name": "WNJD_203_148"
    },
    {
        "name": "WNJD_203_81"
    },
    {
        "name": "WNJD_203_125"
    },
    {
        "name": "WNJD_203_73"
    },
    {
        "name": "WNJD_203_122"
    },
    {
        "name": "WNJD_203_88"
    },
    {
        "name": "WNJD_203_12"
    },
    {
        "name": "WNJD_203_162"
    },
    {
        "name": "WNJD_203_185"
    },
    {
        "name": "WNJD_203_154"
    },
    {
        "name": "WNJD_203_21"
    },
    {
        "name": "WNJD_203_198"
    },
    {
        "name": "WNJD_203_164"
    },
    {
        "name": "WNJD_203_173"
    },
    {
        "name": "WNJD_203_227"
    },
    {
        "name": "WNJD_203_29"
    },
    {
        "name": "WNJD_203_119"
    },
    {
        "name": "WNJD_203_25"
    },
    {
        "name": "WNJD_203_237"
    },
    {
        "name": "WNJD_203_203"
    },
    {
        "name": "WNJD_203_194"
    },
    {
        "name": "WNJD_203_74"
    },
    {
        "name": "WNJD_203_196"
    },
    {
        "name": "WNJD_203_206"
    },
    {
        "name": "WNJD_203_149"
    },
    {
        "name": "WNJD_203_114"
    },
    {
        "name": "WNJD_203_95"
    },
    {
        "name": "WNJD_203_167"
    },
    {
        "name": "WNJD_203_191"
    },
    {
        "name": "WNJD_203_160"
    },
    {
        "name": "WNJD_203_103"
    },
    {
        "name": "WNJD_203_85"
    },
    {
        "name": "WNJD_203_232"
    },
    {
        "name": "WNJD_203_234"
    },
    {
        "name": "WNJD_203_204"
    },
    {
        "name": "WNJD_203_217"
    },
    {
        "name": "WNJD_203_159"
    },
    {
        "name": "WNJD_203_231"
    },
    {
        "name": "WNJD_203_7"
    },
    {
        "name": "WNJD_203_169"
    },
    {
        "name": "WNJD_203_152"
    },
    {
        "name": "WNJD_203_166"
    },
    {
        "name": "WNJD_203_153"
    },
    {
        "name": "WNJD_203_36"
    },
    {
        "name": "WNJD_203_115"
    },
    {
        "name": "WNJD_203_24"
    },
    {
        "name": "WNJD_203_178"
    },
    {
        "name": "WNJD_203_28"
    },
    {
        "name": "WNJD_203_158"
    },
    {
        "name": "WNJD_203_8"
    },
    {
        "name": "WNJD_203_192"
    },
    {
        "name": "WNJD_203_187"
    },
    {
        "name": "WNJD_203_146"
    },
    {
        "name": "WNJD_203_189"
    },
    {
        "name": "WNJD_203_141"
    }
]